[
    {
        "Line1" : "1-5-6, 1108",
        "Line2" : "Higashi-ojima",
        "Pincode": "132-0034",
        "lat": 35.68981,
        "lng": 139.84755,
        "OwnerID": 3
    },
    {
        "Line1" : "1-5-6, 1108",
        "Line2" : "Roppongi",
        "Pincode": "132-0034",
        "lat": 35.660736,
        "lng": 139.72955,
        "OwnerID": 4
    },
    {
        "Line1" : "1-5-6, 1108",
        "Line2" : "ojima",
        "Pincode": "132-0034",
        "lat": 35.883656,
        "lng": 139.82832,
        "OwnerID": 3
    }
]